LICENSE
MANIFEST.in
README.md
setup.cfg
setup.py
skygear/__init__.py
skygear/__version__.py
skygear/action.py
skygear/assets.py
skygear/bin.py
skygear/container.py
skygear/database.py
skygear/decorators.py
skygear/encoding.py
skygear/error.py
skygear/importutil.py
skygear/models.py
skygear/options.py
skygear/predicate.py
skygear/providers.py
skygear/pubsub.py
skygear/query.py
skygear/registry.py
skygear/restful.py
skygear.egg-info/PKG-INFO
skygear.egg-info/SOURCES.txt
skygear.egg-info/dependency_links.txt
skygear.egg-info/entry_points.txt
skygear.egg-info/requires.txt
skygear.egg-info/top_level.txt
skygear/asset/__init__.py
skygear/asset/cloud.py
skygear/asset/common.py
skygear/asset/fs.py
skygear/asset/s3.py
skygear/asset/test_cloud.py
skygear/asset/test_common.py
skygear/asset/test_fs.py
skygear/asset/test_s3.py
skygear/commands/__init__.py
skygear/commands/static_assets.py
skygear/settings/__init__.py
skygear/settings/module.py
skygear/settings/parser.py
skygear/settings/tests/__init__.py
skygear/settings/tests/test_parser.py
skygear/tests/__init__.py
skygear/tests/test_action.py
skygear/tests/test_assets.py
skygear/tests/test_container.py
skygear/tests/test_decorators.py
skygear/tests/test_error.py
skygear/tests/test_importutil.py
skygear/tests/test_models.py
skygear/tests/test_options.py
skygear/tests/test_predicate.py
skygear/tests/test_registry.py
skygear/tests/test_restful.py
skygear/transmitter/__init__.py
skygear/transmitter/common.py
skygear/transmitter/console.py
skygear/transmitter/encoding.py
skygear/transmitter/http.py
skygear/transmitter/zmq.py
skygear/transmitter/tests/__init__.py
skygear/transmitter/tests/test_common.py
skygear/transmitter/tests/test_console.py
skygear/transmitter/tests/test_encoding.py
skygear/transmitter/tests/test_http.py
skygear/transmitter/tests/test_zmq.py
skygear/utils/__init__.py
skygear/utils/assets.py
skygear/utils/context.py
skygear/utils/db.py
skygear/utils/http.py
skygear/utils/logging.py
skygear/utils/user.py
skygear/utils/tests/__init__.py
skygear/utils/tests/test_assets.py
skygear/utils/tests/test_context.py
skygear/utils/tests/test_db.py
skygear/utils/tests/test_user.py