Metadata-Version: 2.1
Name: skygear
Version: 1.7.1
Summary: Python plugin runtime for Skygear
Home-page: https://github.com/SkygearIO/py-skygear
Author: Rick Mak
Author-email: rick.mak@gmail.com
License: Apache License, Version 2.0
Platform: UNKNOWN
Classifier: License :: OSI Approved :: Apache Software License
Classifier: Intended Audience :: Developers
Classifier: Programming Language :: Python :: 3
Classifier: Programming Language :: Python :: 3.3
Classifier: Programming Language :: Python :: 3.4
Classifier: Programming Language :: Python :: 3.5
Classifier: Operating System :: POSIX
Classifier: Operating System :: MacOS :: MacOS X
Classifier: Environment :: Web Environment
Classifier: Development Status :: 3 - Alpha
Provides-Extra: zmq
Provides-Extra: doc
License-File: LICENSE
